InterferencePackage/InterferencePackage.py
InterferencePackage/__init__.py
InterferencePackage/helpers/CameraGrid.py
InterferencePackage/helpers/CrystalGrid.py
InterferencePackage/helpers/CudaWrapper.py
InterferencePackage/helpers/__init__.py
InterferencePackage/tests/__init__.py
InterferencePackage/tests/test_one.py
InterferencePackage-0.0.3.dist-info/DESCRIPTION.rst
InterferencePackage-0.0.3.dist-info/METADATA
InterferencePackage-0.0.3.dist-info/RECORD
InterferencePackage-0.0.3.dist-info/WHEEL
InterferencePackage-0.0.3.dist-info/metadata.json
InterferencePackage-0.0.3.dist-info/top_level.txt
