Metadata-Version: 2.0
Name: InterferencePackage
Version: 0.0.3
Summary: A package for calculating incoherent (or coherent) diffraction images from FELs
Home-page: https://gitlab.physical-engine.de
Author: Stefan Richter
Author-email: stefan.richter@physical-perception.de
License: UNKNOWN
Platform: UNKNOWN
Classifier: Programming Language :: Python :: 2
Classifier: License :: OSI Approved :: MIT License
Classifier: Operating System :: OS Independent
